{
  "Artist": "Schutt, Ellen Isham, 1873-1955",
  "Common name": "oranges",
  "Date created": "1913-08-13",
  "Geographic origin": "Corona, Riverside County, California, United States",
  "Notes on original": "Plot 23, Row 87, Tree 7; One specimen standard fruit; One specimen ridged fruit; Fruits from same tree",
  "Physical description": "1 art original : col. ; 17 x 26 cm.",
  "Scientific name": "Citrus sinensis",
  "Specimen": "63531-b",
  "Variety": "Valencia",
  "Year": "1913",
  "Name": "Citrus sinensis: Valencia"
}